[
  {
    "title": "PHP",
    "code": [
      {
        "name": "Payment Form",
        "version": "1.0f",
        "link": "",
        "zip": "/files/integration/payment_form_payzen_1.0f.zip",
        "label": "payzen",
        "display": ["fr-FR", "en-EN", "de-DE", "pt-BR", "lat", "in", "es-ES"]
      },
      {
        "name": "Payment Form SDK",
        "version": "0.2",
        "link": "https://github.com/lyra/php-payment-form-examples",
        "zip": "https://github.com/lyra/php-payment-form-examples/archive/master.zip",
        "label": "payzen",
        "display": ["fr-FR", "en-EN", "de-DE", "pt-BR", "lat", "in", "es-ES"]
      },
      {
        "name": "Webservices ws-v5",
        "version": "1.4",
        "link": "https://github.com/payzen/soap-v5-payment-exemple-php",
        "zip": "https://github.com/payzen/soap-v5-payment-exemple-php/archive/master.zip",
        "label": "payzen",
        "display": ["fr-FR", "en-EN", "de-DE", "pt-BR", "lat", "es-ES"]
      },
      {
        "name": "Webservices ws-v4",
        "version": "",
        "link": "",
        "zip": "/files/integration/PayZen_pack_php_ws-v4.zip",
        "label": "payzen",
        "display": ["fr-FR", "en-EN", "de-DE", "pt-BR", "lat", "es-ES"]
      }
    ]
  },
  {
    "title": "Python",
    "code": [
      {
        "name": "Payment Form",
        "version": "3.4",
        "link": "https://github.com/lyra/python-payment-form-examples",
        "zip": "https://github.com/lyra/python-payment-form-examples/archive/master.zip",
        "label": "payzen",
        "display": ["fr-FR", "en-EN", "de-DE", "pt-BR", "lat", "in", "es-ES"]
      },
      {
        "name": "Webservices ws-v5",
        "version": "1.4",
        "link": "https://github.com/payzen/ws-v5-createPayment-python",
        "zip": "https://github.com/payzen/ws-v5-createPayment-python/archive/master.zip",
        "label": "payzen",
        "display": ["fr-FR", "en-EN", "de-DE", "pt-BR", "lat", "es-ES"]
      }
    ]
  },
  {
    "title": "JAVA",
    "code": [
      {
        "name": "Webservices v5 - SDK",
        "version": "1.0.6",
        "link": "https://github.com/payzen/payzen-webservices-v5-sdk-java",
        "zip": "https://github.com/payzen/payzen-webservices-v5-sdk-java/archive/master.zip",
        "label": "payzen",
        "display": ["fr-FR", "en-EN", "de-DE", "pt-BR", "lat", "es-ES"]
      },
      {
        "name": "Webservices v5",
        "version": "1.5",
        "link": "https://github.com/payzen/payzen-soapwebservice-java-example",
        "zip": "https://github.com/payzen/payzen-soapwebservice-java-example/archive/master.zip",
        "label": "payzen",
        "display": ["fr-FR", "en-EN", "de-DE", "pt-BR", "lat", "es-ES"]
      }
    ]
  },
  {
    "title": "ASP",
    "code": [
      {
        "name": "Payment Form",
        "version": "",
        "link": "https://github.com/lyra/asp-payment-form-examples",
        "zip": "https://github.com/lyra/asp-payment-form-examples/archive/master.zip",
        "label": "payzen",
        "display": ["fr-FR", "en-EN", "de-DE", "pt-BR", "lat", "in", "es-ES"]
      }
    ]
  }
]