[
  {
    "title": "PHP",
    "code": [
      {
        "name": "Payment Form",
        "version": "0.2.1",
        "link": false,
        "zip": "https://github.com/lyra/php-payment-form-examples/releases/download/v0.2.1/ClicAndPay_By_groupe_Credit_du_Nord_php-payment-form-examples_v0.2.1.zip",
        "display": ["fr-FR"]
      }
    ]
  },
  {
    "title": "Python",
    "code": [
      {
        "name": "Payment Form",
        "version": "0.2.1",
        "link": false,
        "zip": "https://github.com/lyra/python-payment-form-examples/releases/download/v0.1.0/ClicAndPay_By_groupe_Credit_du_Nord_python-payment-form-examples_v0.1.0.zip",
        "display": ["fr-FR"]
      }
    ]
  },
  {
    "title": "ASP",
    "code": [
      {
        "name": "Payment Form",
        "version": "0.2.1",
        "link": false,
        "zip": "https://github.com/lyra/asp-payment-form-examples/releases/download/v0.1.0/ClicAndPay_By_groupe_Credit_du_Nord_asp-payment-form-examples_v0.1.0.zip",
        "display": ["fr-FR"]
      }
    ]
  },
  {
    "title": "JAVA",
    "code": [
      {
        "name": "Mobile payment Server integration",
        "version": "1.1",
        "link": false,
        "zip": "https://github.com/lyra/webview-payment-sparkjava-integration-sample",
        "display": ["fr-FR", "en-EN"]
      }
    ]
  },
  {
    "title": "Kotlin",
    "code": [
      {
        "name": "Mobile payment via webview",
        "version": "1.1",
        "zip": "https://github.com/lyra/webview-payment-android-integration-sample",
        "link": false,
        "display": ["fr-FR", "en-EN"]
      }
    ]
  },
  {
    "title": "Swift",
    "code": [
      {
        "name": "Mobile payment via webview",
        "version": "1.1",
        "zip": "https://github.com/lyra/webview-payment-ios-integration-sample",
        "link": false,
        "display": ["fr-FR", "en-EN"]
      }
    ]
  }
]
